[{"id":0,"href":"/articles/test/","title":"Test","section":"Articles","content":" これはテストです # "},{"id":1,"href":"/articles/example/","title":"Example","section":"Articles","content":" Example # Lorem ipsum dolor sit amet, consectetur adipiscing elit, sed do eiusmod tempor incididunt ut labore et dolore magna aliqua. Ut enim ad minim veniam, quis nostrud exercitation ullamco laboris nisi ut aliquip ex ea commodo consequat. Duis aute irure dolor in reprehenderit in voluptate velit esse cillum dolore eu fugiat nulla pariatur. Excepteur sint occaecat cupidatat non proident, sunt in culpa qui officia deserunt mollit anim id est laborum.\n"},{"id":2,"href":"/members/","title":"Members","section":"北海道大学医学部 Bioinfo研究会","content":"Comming soon\u0026hellip;\n"},{"id":3,"href":"/about/","title":"About Us","section":"北海道大学医学部 Bioinfo研究会","content":"私たちは北海道大学医学部に在学する学生によって構成されている学生団体です. バイオインフォマティクスや広く情報科学ついて学習し合っている団体です．\n"}]